decisiontree_to_sankey/__init__.py
decisiontree_to_sankey/decisiontree_to_sankey.py
decisiontree_to_sankey-0.2.dist-info/LICENSE
decisiontree_to_sankey-0.2.dist-info/METADATA
decisiontree_to_sankey-0.2.dist-info/WHEEL
decisiontree_to_sankey-0.2.dist-info/top_level.txt
decisiontree_to_sankey-0.2.dist-info/RECORD
