Metadata-Version: 2.1
Name: decisiontree-to-sankey
Version: 0.2
Summary: A package to visualize decision trees as Sankey diagrams using Plotly.
Home-page: https://github.com/LukeADay/DecisionTree-to-Sankey
Author: Luke Day
Author-email: luke.alexander.day@gmail.com
Requires-Python: >=3.6
License-File: LICENSE
Requires-Dist: pandas
Requires-Dist: numpy
Requires-Dist: scikit-learn
Requires-Dist: plotly
Requires-Dist: seaborn
